{"frames": {

"Minotaur_03_Walking_004.png":
{
	"frame": {"x":1,"y":1,"w":422,"h":415},
	"rotated": false,
	"trimmed": true,
	"spriteSourceSize": {"x":220,"y":38,"w":422,"h":415},
	"sourceSize": {"w":720,"h":490}
},
"Minotaur_03_Walking_005.png":
{
	"frame": {"x":425,"y":1,"w":418,"h":416},
	"rotated": true,
	"trimmed": true,
	"spriteSourceSize": {"x":218,"y":38,"w":418,"h":416},
	"sourceSize": {"w":720,"h":490}
},
"Minotaur_03_Walking_006.png":
{
	"frame": {"x":419,"y":421,"w":410,"h":418},
	"rotated": true,
	"trimmed": true,
	"spriteSourceSize": {"x":219,"y":38,"w":410,"h":418},
	"sourceSize": {"w":720,"h":490}
},
"Minotaur_03_Walking_013.png":
{
	"frame": {"x":1,"y":418,"w":414,"h":416},
	"rotated": true,
	"trimmed": true,
	"spriteSourceSize": {"x":221,"y":38,"w":414,"h":416},
	"sourceSize": {"w":720,"h":490}
}},
"animations": {
	"Minotaur_03_Walking": ["Minotaur_03_Walking_004.png","Minotaur_03_Walking_005.png","Minotaur_03_Walking_006.png","Minotaur_03_Walking_013.png"]
},
"meta": {
	"app": "https://www.codeandweb.com/texturepacker",
	"version": "1.0",
	"image": "minotaur03-2.png",
	"format": "RGBA8888",
	"size": {"w":842,"h":833},
	"scale": "1",
	"related_multi_packs": [ "minotaur03-0.json", "minotaur03-1.json", "minotaur03-3.json", "minotaur03-4.json" ],
	"smartupdate": "$TexturePacker:SmartUpdate:9a23ee5f751823b88e65a2aa2afde4d7:dbd8c71a2698ae06adebfa3dbea9b82f:0f740ba109e734613b6b9ec6212408b0$"
}
}
